LICENCE.txt
MANIFEST.in
README.rst
setup.py
Gestus_client.egg-info/PKG-INFO
Gestus_client.egg-info/SOURCES.txt
Gestus_client.egg-info/dependency_links.txt
Gestus_client.egg-info/entry_points.txt
Gestus_client.egg-info/not-zip-safe
Gestus_client.egg-info/requires.txt
Gestus_client.egg-info/top_level.txt
gestus_client/__init__.py
gestus_client/cli.py
gestus_client/client.py
gestus_client/config.py
gestus_client/egg_finder.py
gestus_client/logging_handler.py