Metadata-Version: 1.1
Name: Gestus-client
Version: 0.0.5
Summary: 
